Workbook

Sheet README_PILOT
A1: FICHA TÉCNICA DEL PILOTO DE PRUEBA
A3: Atributo del Piloto | B3: Valor / Descripción de Configuración
A4: pilot_id | B4: PILOT_004
A5: case_option | B5: CASH_BANK_OR_SIMPLE_RECONCILIATION
A6: tipo | B6: XLSX sintético externo
A7: propósito | B7: Probar el comportamiento del motor Primeros Auxilios GPT V1 en un caso de caja, banco y conciliación simple.
A8: límite | B8: Validar de forma prudente el límite entre movimientos observables, conciliación parcial y conciliación real (no afirmable sin segunda fuente suficiente). El sistema no debe diagnosticar fraude ni errores contables definitivos si la evidencia es unilateral.
A9: uso | B9: Evidencia sintética para registro documental interno y calibración de señales de control, no apto para ejecución en runtime real.

Sheet Categorias
A1: CATÁLOGOS DEL SISTEMA DE AUDITORÍA
A3: first_aid_option | B3: admission_verdict | C3: final_verdict | D3: Señal First Aid | E3: Límite owner-safe (Definición Prudente)
A4: CASH_BANK_OR_SIMPLE_RECONCILIATION | B4: ACCEPTED | C4: SUCCESS | D4: OK_COINCIDENTE | E4: Movimiento comparable entre fuentes, no implica auditoría completa.
B5: BLOCKED | C5: PARTIAL | D5: DIFERENCIA_MENOR_COMISION | E5: Diferencia compatible con comisión o retención, requiere validar liquidación.
B6: OUT_OF_SCOPE | C6: BLOCKED | D6: BANCO_SIN_CONTRAPARTE | E6: Movimiento visible en banco sin fuente equivalente en caja/POS.
B7: ESCALATE | C7: OUT_OF_SCOPE | D7: CAJA_SIN_BANCO | E7: Movimiento visible en caja/POS sin contraparte bancaria.
C8: ESCALATED_TO_LEVEL_2 | D8: IMPORTE_FALTANTE | E8: Monto no registrado en una o más fuentes documentales.
D9: IMPORTE_AMBIGUO_NO_COMPARABLE | E9: Dato ambiguo; no calcular silenciosamente.
D10: IMPORTE_CERO_A_CONFIRMAR | E10: Importe en cero bajo condición sospechosa, requiere verificación de origen.
D11: POSIBLE_DUPLICADO | E11: Transacción con idénticos atributos en el mismo período, verificar duplicación.
D12: FECHA_FUERA_DE_PERIODO | E12: Fecha informada no corresponde al marco temporal bajo revisión.
D13: RETIRO_DECLARADO | E13: Retiro de fondos por parte del propietario, requiere rendición de cuenta.
D14: NO_CONCILIABLE_CON_UNA_FUENTE | E14: Con una sola fuente se puede marcar señal, no cerrar conciliación.

Sheet Caja_Banco
A1: ID movimiento | B1: Fecha | C1: Fuente | D1: Tipo movimiento | E1: Descripción | F1: Importe declarado | G1: Importe banco | H1: Importe caja/POS | I1: Medio de pago | J1: Referencia externa | K1: Estado esperado | L1: Observación dueño | M1: Diferencia banco vs caja | N1: Señal First Aid | O1: Límite owner-safe
A2: MOV-001 | B2: 2026-06-01 | C2: Banco | D2: Ingreso | E2: Venta local estándar | F2: 15000 | G2: 15000 | H2: 15000 | I2: Tarjeta | J2: REF-101 | K2: OK_COINCIDENTE | L2: Venta de mostrador cobrada por terminal | M2: =IF(OR(ISTEXT(G2),ISTEXT(H2)), "N/A", IF(OR(ISBLANK(G2),ISBLANK(H2)), G2-IF(ISBLANK(H2),0,H2), G2-H2)) | N2: =K2 | O2: =VLOOKUP(N2, Categorias!$D$4:$E$14, 2, FALSE)
A3: MOV-002 | B3: 2026-06-02 | C3: Mercado Pago | D3: Ingreso | E3: Cobro online plataforma | F3: 10000 | G3: 9500 | H3: 10000 | I3: Transferencia | J3: REF-102 | K3: DIFERENCIA_MENOR_COMISION | L3: Cobro neto con retención de comisión estándar | M3: =IF(OR(ISTEXT(G3),ISTEXT(H3)), "N/A", IF(OR(ISBLANK(G3),ISBLANK(H3)), G3-IF(ISBLANK(H3),0,H3), G3-H3)) | N3: =K3 | O3: =VLOOKUP(N3, Categorias!$D$4:$E$14, 2, FALSE)
A4: MOV-003 | B4: 2026-06-03 | C4: Banco | D4: Egreso | E4: Mantenimiento cuenta | F4: 2500 | G4: 2500 | H4: 0 | I4: Débito aut | J4: REF-103 | K4: BANCO_SIN_CONTRAPARTE | L4: Cargo automático del banco, no cargado en caja | M4: =IF(OR(ISTEXT(G4),ISTEXT(H4)), "N/A", IF(OR(ISBLANK(G4),ISBLANK(H4)), G4-IF(ISBLANK(H4),0,H4), G4-H4)) | N4: =K4 | O4: =VLOOKUP(N4, Categorias!$D$4:$E$14, 2, FALSE)
A5: MOV-004 | B5: 2026-06-04 | C5: Caja diaria | D5: Ingreso | E5: Venta efectivo salón | F5: 8000 | G5: 0 | H5: 8000 | I5: Efectivo | J5: REF-104 | K5: CAJA_SIN_BANCO | L5: Efectivo guardado físicamente en caja fuerte | M5: =IF(OR(ISTEXT(G5),ISTEXT(H5)), "N/A", IF(OR(ISBLANK(G5),ISBLANK(H5)), G5-IF(ISBLANK(H5),0,H5), G5-H5)) | N5: =K5 | O5: =VLOOKUP(N5, Categorias!$D$4:$E$14, 2, FALSE)
A6: MOV-005 | B6: 2026-06-05 | C6: Banco | D6: Egreso | E6: Reversa de cargo a cliente | F6: -4500 | G6: -4500 | H6: -4500 | I6: Transferencia | J6: REF-105 | K6: OK_COINCIDENTE | L6: Importe negativo válido por nota de crédito | M6: =IF(OR(ISTEXT(G6),ISTEXT(H6)), "N/A", IF(OR(ISBLANK(G6),ISBLANK(H6)), G6-IF(ISBLANK(H6),0,H6), G6-H6)) | N6: =K6 | O6: =VLOOKUP(N6, Categorias!$D$4:$E$14, 2, FALSE)
A7: MOV-006 | B7: 2026-06-06 | C7: POS | D7: Ingreso | E7: Prueba terminal posnet | F7: 0 | G7: 0 | H7: 0 | I7: Tarjeta | J7: REF-106 | K7: IMPORTE_CERO_A_CONFIRMAR | L7: Monto cero registrado, verificar si fue rechazada | M7: =IF(OR(ISTEXT(G7),ISTEXT(H7)), "N/A", IF(OR(ISBLANK(G7),ISBLANK(H7)), G7-IF(ISBLANK(H7),0,H7), G7-H7)) | N7: =K7 | O7: =VLOOKUP(N7, Categorias!$D$4:$E$14, 2, FALSE)
A8: MOV-007 | B8: 2026-06-07 | C8: Banco | D8: Ingreso | E8: Transferencia recibida cta | F8: 12000 | G8: 12000 | I8: Transferencia | J8: REF-107 | K8: IMPORTE_FALTANTE | L8: Falta registrar el importe en la planilla interna de caja | M8: =IF(OR(ISTEXT(G8),ISTEXT(H8)), "N/A", IF(OR(ISBLANK(G8),ISBLANK(H8)), G8-IF(ISBLANK(H8),0,H8), G8-H8)) | N8: =K8 | O8: =VLOOKUP(N8, Categorias!$D$4:$E$14, 2, FALSE)
A9: MOV-008 | B9: 2026-06-08 | C9: Caja diaria | D9: Ingreso | E9: Ajuste manual de caja | F9: 12,34,56 | G9: 0 | H9: 12,34,56 | I9: Efectivo | J9: REF-108 | K9: IMPORTE_AMBIGUO_NO_COMPARABLE | L9: Importe textual ambiguo ingresado por error | M9: =IF(OR(ISTEXT(G9),ISTEXT(H9)), "N/A", IF(OR(ISBLANK(G9),ISBLANK(H9)), G9-IF(ISBLANK(H9),0,H9), G9-H9)) | N9: =K9 | O9: =VLOOKUP(N9, Categorias!$D$4:$E$14, 2, FALSE)
A10: MOV-009 | B10: 2026-06-09 | C10: Banco | D10: Ingreso | E10: Pago cliente formato regional | F10: $ 148.200,50 | G10: 148200.5 | H10: 148200.5 | I10: Transferencia | J10: REF-109 | K10: IMPORTE_AMBIGUO_NO_COMPARABLE | L10: Formato argentino ingresado como texto literal | M10: =IF(OR(ISTEXT(G10),ISTEXT(H10)), "N/A", IF(OR(ISBLANK(G10),ISBLANK(H10)), G10-IF(ISBLANK(H10),0,H10), G10-H10)) | N10: =K10 | O10: =VLOOKUP(N10, Categorias!$D$4:$E$14, 2, FALSE)
A11: MOV-010 | B11: 2026-06-10 | C11: Banco | D11: Ingreso | E11: Cobro lote tarjetas | F11: 5000 | G11: 5000 | H11: 5000 | I11: Tarjeta | J11: REF-110 | K11: POSIBLE_DUPLICADO | L11: Posible duplicado de lote, verificar liquidación | M11: =IF(OR(ISTEXT(G11),ISTEXT(H11)), "N/A", IF(OR(ISBLANK(G11),ISBLANK(H11)), G11-IF(ISBLANK(H11),0,H11), G11-H11)) | N11: =K11 | O11: =VLOOKUP(N11, Categorias!$D$4:$E$14, 2, FALSE)
A12: MOV-011 | B12: 2026-06-10 | C12: Banco | D12: Ingreso | E12: Cobro lote tarjetas | F12: 5000 | G12: 5000 | H12: 5000 | I12: Tarjeta | J12: REF-110 | K12: POSIBLE_DUPLICADO | L12: Mismo importe, fecha y referencia externa | M12: =IF(OR(ISTEXT(G12),ISTEXT(H12)), "N/A", IF(OR(ISBLANK(G12),ISBLANK(H12)), G12-IF(ISBLANK(H12),0,H12), G12-H12)) | N12: =K12 | O12: =VLOOKUP(N12, Categorias!$D$4:$E$14, 2, FALSE)
A13: MOV-012 | B13: 2026-06-11 | C13: POS | D13: Ingreso | E13: Venta mostrador sin ref | F13: 3400 | G13: 3400 | H13: 3400 | I13: Tarjeta | K13: OK_COINCIDENTE | L13: Referencia externa faltante pero valores coinciden exactos | M13: =IF(OR(ISTEXT(G13),ISTEXT(H13)), "N/A", IF(OR(ISBLANK(G13),ISBLANK(H13)), G13-IF(ISBLANK(H13),0,H13), G13-H13)) | N13: =K13 | O13: =VLOOKUP(N13, Categorias!$D$4:$E$14, 2, FALSE)
A14: MOV-013 | B14: 2026-06-12 | C14: Caja diaria | D14: Egreso | E14: Retiro personal de socios | F14: 20000 | G14: 0 | H14: 20000 | I14: Efectivo | J14: REF-113 | K14: RETIRO_DECLARADO | L14: Retiro del dueño declarado formalmente | M14: =IF(OR(ISTEXT(G14),ISTEXT(H14)), "N/A", IF(OR(ISBLANK(G14),ISBLANK(H14)), G14-IF(ISBLANK(H14),0,H14), G14-H14)) | N14: =K14 | O14: =VLOOKUP(N14, Categorias!$D$4:$E$14, 2, FALSE)
A15: MOV-014 | B15: 2026-06-13 | C15: Mercado Pago | D15: Egreso | E15: Comisión Mercado Pago | F15: 450 | G15: 0 | H15: 450 | I15: Transferencia | J15: REF-114 | K15: DIFERENCIA_MENOR_COMISION | L15: Gasto operativo deducido por la billetera virtual | M15: =IF(OR(ISTEXT(G15),ISTEXT(H15)), "N/A", IF(OR(ISBLANK(G15),ISBLANK(H15)), G15-IF(ISBLANK(H15),0,H15), G15-H15)) | N15: =K15 | O15: =VLOOKUP(N15, Categorias!$D$4:$E$14, 2, FALSE)
A16: MOV-015 | B16: 2026-06-14 | C16: Banco | D16: Ingreso | E16: Transferencia sin id | F16: 18500 | G16: 18500 | H16: 0 | I16: Transferencia | J16: REF-115 | K16: NO_CONCILIABLE_CON_UNA_FUENTE | L16: Transferencia bancaria sin identificación de contraparte | M16: =IF(OR(ISTEXT(G16),ISTEXT(H16)), "N/A", IF(OR(ISBLANK(G16),ISBLANK(H16)), G16-IF(ISBLANK(H16),0,H16), G16-H16)) | N16: =K16 | O16: =VLOOKUP(N16, Categorias!$D$4:$E$14, 2, FALSE)
A17: MOV-016 | B17: 2025-12-31 | C17: Banco | D17: Ingreso | E17: Ajuste saldo inicial anterior | F17: 6000 | G17: 6000 | H17: 6000 | I17: Transferencia | J17: REF-116 | K17: FECHA_FUERA_DE_PERIODO | L17: Fecha fuera de período de auditoría actual | M17: =IF(OR(ISTEXT(G17),ISTEXT(H17)), "N/A", IF(OR(ISBLANK(G17),ISBLANK(H17)), G17-IF(ISBLANK(H17),0,H17), G17-H17)) | N17: =K17 | O17: =VLOOKUP(N17, Categorias!$D$4:$E$14, 2, FALSE)
A18: MOV-017 | B18: 2026-06-15 | C18: Banco | D18: Ingreso | E18: Venta web regular | F18: 7500 | G18: 7500 | H18: 7500 | I18: Tarjeta | J18: REF-117 | K18: OK_COINCIDENTE | L18: Conciliación exacta estándar | M18: =IF(OR(ISTEXT(G18),ISTEXT(H18)), "N/A", IF(OR(ISBLANK(G18),ISBLANK(H18)), G18-IF(ISBLANK(H18),0,H18), G18-H18)) | N18: =K18 | O18: =VLOOKUP(N18, Categorias!$D$4:$E$14, 2, FALSE)
A19: MOV-018 | B19: 2026-06-16 | C19: Caja diaria | D19: Egreso | E19: Pago limpieza salón | F19: 12000 | G19: 0 | H19: 12000 | I19: Efectivo | J19: REF-118 | K19: CAJA_SIN_BANCO | L19: Gasto menor liquidado puramente en efectivo | M19: =IF(OR(ISTEXT(G19),ISTEXT(H19)), "N/A", IF(OR(ISBLANK(G19),ISBLANK(H19)), G19-IF(ISBLANK(H19),0,H19), G19-H19)) | N19: =K19 | O19: =VLOOKUP(N19, Categorias!$D$4:$E$14, 2, FALSE)
A20: MOV-019 | B20: 2026-06-17 | C20: Banco | D20: Egreso | E20: Impuesto al cheque deb | F20: 120 | G20: 120 | H20: 0 | I20: Débito aut | J20: REF-119 | K20: BANCO_SIN_CONTRAPARTE | L20: Impuesto gubernamental debitado directo de cuenta | M20: =IF(OR(ISTEXT(G20),ISTEXT(H20)), "N/A", IF(OR(ISBLANK(G20),ISBLANK(H20)), G20-IF(ISBLANK(H20),0,H20), G20-H20)) | N20: =K20 | O20: =VLOOKUP(N20, Categorias!$D$4:$E$14, 2, FALSE)
A21: MOV-020 | B21: 2026-06-18 | C21: POS | D21: Ingreso | E21: Cobro provisional unilat | F21: 4500 | G21: 4500 | H21: 0 | I21: Tarjeta | J21: REF-120 | K21: NO_CONCILIABLE_CON_UNA_FUENTE | L21: Información unilateral de un solo canal, no cerrar conciliación | M21: =IF(OR(ISTEXT(G21),ISTEXT(H21)), "N/A", IF(OR(ISBLANK(G21),ISBLANK(H21)), G21-IF(ISBLANK(H21),0,H21), G21-H21)) | N21: =K21 | O21: =VLOOKUP(N21, Categorias!$D$4:$E$14, 2, FALSE)

Sheet Revision_PymIA
A1: INFORME DE ADMISIÓN Y RESUMEN AUTOMÁTICO DE SEÑALES
A3: pilot_id | B3: PILOT_004
A4: case_option | B4: CASH_BANK_OR_SIMPLE_RECONCILIATION
A5: evidence_type | B5: XLSX_SYNTHETIC
A6: admission_verdict | B6: ACCEPTED
A8: Criterio Cualitativo / Marco de Control | B8: Dictamen de Borde Técnico / Prudencia Profesional
A9: what_can_be_reviewed | B9: Revisión preliminar de movimientos declarados por el propietario y correspondencia matemática inicial entre los registros documentales provistos.
A10: what_cannot_be_claimed | B10: Prohibido afirmar fraude, dolo, intencionalidad, pérdida contable definitiva o dar por cerrada una conciliación real. La evidencia unilateral es de carácter preliminar.
A11: missing_evidence | B11: Extractos bancarios oficiales digitalizados de fuentes independientes, liquidaciones de tarjetas POS (Mercado Pago, Fiserv) y arqueos físicos presenciales de caja.
A12: healthy_block | B12: Subconjunto de transacciones perfectamente coincidentes en fecha, importe y descripción, junto con descalces menores correspondientes a comisiones de pasarela bancaria.
A13: next_step | B13: Solicitar formalmente la segunda fuente documental cruzada independiente para los registros que poseen conciliación unilateral o parcial, y rectificar importes ambiguos.
A15: Métrica / Señal First Aid Evaluada | B15: Conteo Automático (Fórmula Excel)
A16: Total movimientos | B16: =COUNTA(Caja_Banco!$A$2:$A$21)
A17: OK coincidente | B17: =COUNTIF(Caja_Banco!$N$2:$N$21, "OK_COINCIDENTE")
A18: Diferencia menor comisión | B18: =COUNTIF(Caja_Banco!$N$2:$N$21, "DIFERENCIA_MENOR_COMISION")
A19: Banco sin contraparte | B19: =COUNTIF(Caja_Banco!$N$2:$N$21, "BANCO_SIN_CONTRAPARTE")
A20: Caja sin banco | B20: =COUNTIF(Caja_Banco!$N$2:$N$21, "CAJA_SIN_BANCO")
A21: Importe faltante | B21: =COUNTIF(Caja_Banco!$N$2:$N$21, "IMPORTE_FALTANTE")
A22: Importe ambiguo no comparable | B22: =COUNTIF(Caja_Banco!$N$2:$N$21, "IMPORTE_AMBIGUO_NO_COMPARABLE")
A23: Importe cero a confirmar | B23: =COUNTIF(Caja_Banco!$N$2:$N$21, "IMPORTE_CERO_A_CONFIRMAR")
A24: Posible duplicado | B24: =COUNTIF(Caja_Banco!$N$2:$N$21, "POSIBLE_DUPLICADO")
A25: Fecha fuera de período | B25: =COUNTIF(Caja_Banco!$N$2:$N$21, "FECHA_FUERA_DE_PERIODO")
A26: Retiro declarado | B26: =COUNTIF(Caja_Banco!$N$2:$N$21, "RETIRO_DECLARADO")
A27: No conciliable con una fuente | B27: =COUNTIF(Caja_Banco!$N$2:$N$21, "NO_CONCILIABLE_CON_UNA_FUENTE")
