Workbook

Sheet productos
A1: sku | B1: producto | C1: categoría | D1: talle | E1: color | F1: proveedor_principal | G1: costo_unitario_actual | H1: precio_minorista | I1: precio_mayorista | J1: margen_objetivo_pct | K1: stock_minimo | L1: activo
A2: REM-001 | B2: Remera Algodón Básica | C2: remeras | D2: M | E2: Negro | F2: Textil Avellaneda | G2: 4500 | H2: 12500 | I2: 8200 | J2: 0.6 | K2: 60 | L2: SI
A3: REM-002 | B3: Remera Algodón Básica | C3: remeras | D3: L | E3: Blanco | F3: Textil Avellaneda | G3: 4500 | H3: 12500 | I3: 8200 | J3: 0.6 | K3: 60 | L3: SI
A4: REM-003 | B4: Remera Estampada Urban | C4: remeras | D4: S | E4: Gris Melange | F4: Estampados JC | G4: 5500 | H4: 15500 | I4: 9900 | J4: 0.6 | K4: 40 | L4: SI
A5: REM-004 | B5: Remera Oversize Vint | C5: remeras | D5: XL | E5: Azul Aero | F5: Estampados JC | G5: 6200 | H5: 17800 | I5: 11500 | J5: 0.6 | K5: 30 | L5: SI
A6: BUZ-001 | B6: Buzo Canguro con Frisa | C6: buzos | D6: M | E6: Gris Topo | F6: Confecciones Delta | G6: 13000 | H6: 34000 | I6: 22000 | J6: 0.55 | K6: 40 | L6: SI
A7: BUZ-002 | B7: Buzo Canguro con Frisa | C7: buzos | D7: L | E7: Negro | F7: Confecciones Delta | G7: 13000 | H7: 34000 | I7: 22000 | J7: 0.55 | K7: 40 | L7: SI
A8: BUZ-003 | B8: Buzo Cuello Redondo Premium | C8: buzos | D8: M | E8: Verde Militar | F8: Sudaderas Arg | G8: 14500 | H8: 38500 | I8: 25000 | J8: 0.55 | K8: 25 | L8: SI
A9: CAM-001 | B9: Campera Trucker Impermeable | C9: camperas | D9: L | E9: Negro | F9: Abrigos Polar Sur | G9: 26000 | H9: 69000 | I9: 44000 | J9: 0.55 | K9: 20 | L9: SI
A10: CAM-002 | B10: Campera de Abrigo Invierno | C10: camperas | D10: XL | E10: Azul Marino | F10: Abrigos Polar Sur | G10: 34000 | H10: 88000 | I10: 54000 | J10: 0.55 | K10: 15 | L10: SI
A11: CAM-003 | B11: Campera Rompevientos Light | C11: camperas | D11: S | E11: Rojo | F11: Textil Avellaneda | G11: 16000 | H11: 42000 | I11: 27000 | J11: 0.55 | K11: 15 | L11: SI
A12: PAN-001 | B12: Pantalón Jean Chupín | C12: pantalones | D12: 42 | E12: Azul Localizado | F12: Jeans del Oeste | G12: 16500 | H12: 44000 | I12: 28000 | J12: 0.55 | K12: 35 | L12: SI
A13: PAN-002 | B13: Pantalón Jean Recto | C13: pantalones | D13: 44 | E13: Negro Gastado | F13: Jeans del Oeste | G13: 16500 | H13: 44000 | I13: 28000 | J13: 0.55 | K13: 30 | L13: SI
... A23: ACC-003 | B23: Mochila Urbana Porta Notebook | C23: accesorios | D23: Único | E23: Gris Oscuro | F23: Importaciones Baires | G23: 19500 | H23: 52000 | I23: 33000 | J23: 0.55 | K23: 12 | L23: SI

Sheet ventas
A1: fecha | B1: comprobante | C1: canal | D1: cliente | E1: sku | F1: producto | G1: cantidad | H1: precio_unitario_vendido | I1: descuento_pct | J1: medio_cobro | K1: plazo_cobro_dias | L1: importe_total
A2: 2026-03-04 | B2: FA-0002001 | C2: minorista | D2: Consumidor Final | E2: REM-003 | F2: Remera Estampada Urban | G2: 3 | H2: 15500 | I2: 0 | J2: transferencia | K2: 0 | L2: 46500
A3: 2026-03-05 | B3: FA-0002002 | C3: minorista | D3: Consumidor Final | E3: MED-001 | F3: Medias Element Pack x3 | G3: 3 | H3: 5400 | I3: 0 | J3: efectivo | K3: 0 | L3: 16200
A4: 2026-03-05 | B4: FA-0002003 | C4: showroom | D4: Consumidor Final | E4: CAL-001 | F4: Calza Deportiva Alta Cintura | G4: 2 | H4: 23000 | I4: 0 | J4: mercado_pago | K4: 0 | L4: 46000
A5: 2026-03-05 | B5: FA-0002004 | C5: mayorista | D5: Juan Perez | E5: REM-001 | F5: Remera Algodón Básica | G5: 19 | H5: 8200 | I5: 0 | J5: cuenta_corriente | K5: 30 | L5: 155800
A6: 2026-03-05 | B6: FA-0002005 | C6: minorista | D6: Consumidor Final | E6: ACC-001 | F6: Gorra Trucker Urbana | G6: 3 | H6: 11000 | I6: 0.05 | J6: mercado_pago | K6: 0 | L6: 31350
A7: 2026-03-07 | B7: FA-0002006 | C7: online | D7: Consumidor Final | E7: REM-003 | F7: Remera Estampada Urban | G7: 4 | H7: 15500 | I7: 0 | J7: mercado_pago | K7: 0 | L7: 62000
A8: 2026-03-07 | B8: FA-0002007 | C8: showroom | D8: Consumidor Final | E8: MED-002 | F8: Soberanas Invisibles Pack x3 | G8: 1 | H8: 4600 | I8: 0.05 | J8: transferencia | K8: 0 | L8: 4370
A9: 2026-03-07 | B9: FA-0002008 | C9: online | D9: Consumidor Final | E9: REM-004 | F9: Remera Oversize Vint | G9: 2 | H9: 17800 | I9: 0 | J9: transferencia | K9: 0 | L9: 35600
A10: 2026-03-08 | B10: FA-0002009 | C10: showroom | D10: Consumidor Final | E10: MED-001 | F10: Medias Element Pack x3 | G10: 2 | H10: 5400 | I10: 0 | J10: mercado_pago | K10: 0 | L10: 10800
A11: 2026-03-08 | B11: FA-0002010 | C11: minorista | D11: Consumidor Final | E11: REM-001 | F11: Remera Algodón Básica | G11: 4 | H11: 12500 | I11: 0 | J11: mercado_pago | K11: 0 | L11: 50000
A12: 2026-03-08 | B12: FA-0002011 | C12: minorista | D12: Consumidor Final | E12: REM-001 | F12: Remera Algodón Básica | G12: 2 | H12: 12500 | I12: 0 | J12: transferencia | K12: 0 | L12: 25000
A13: 2026-03-12 | B13: FA-0002012 | C13: online | D13: Consumidor Final | E13: PAN-001 | F13: Pantalón Jean Chupín | G13: 4 | H13: 44000 | I13: 0 | J13: efectivo | K13: 0 | L13: 176000
... A123: 2026-05-30 | B123: FA-0002122 | C123: online | D123: Consumidor Final | E123: TOP-001 | F123: Top Deportivo Suplex | G123: 1 | H123: 14900 | I123: 0 | J123: mercado_pago | K123: 0 | L123: 14900

Sheet compras
A1: fecha | B1: orden_compra | C1: proveedor | D1: sku | E1: producto | F1: cantidad_comprada | G1: costo_unitario | H1: importe_total | I1: fecha_pago | J1: estado_pago
A2: 2026-03-05 | B2: OC-101 | C2: Textil Avellaneda | D2: REM-001 | E2: Remera Algodón Básica | F2: 27 | G2: 4140 | H2: 111780 | I2: 2026-03-20 | J2: PAGADO
A3: 2026-03-05 | B3: OC-101 | C3: Textil Avellaneda | D3: REM-002 | E3: Remera Algodón Básica | F3: 23 | G3: 4140 | H3: 95220 | I3: 2026-03-20 | J3: PAGADO
A4: 2026-03-05 | B4: OC-101 | C4: Estampados JC | D4: REM-003 | E4: Remera Estampada Urban | F4: 30 | G4: 5060 | H4: 151800 | I4: 2026-03-20 | J4: PAGADO
A5: 2026-03-05 | B5: OC-101 | C5: Estampados JC | D5: REM-004 | E5: Remera Oversize Vint | F5: 19 | G5: 5704 | H5: 108376 | I5: 2026-03-20 | J5: PAGADO
A6: 2026-03-05 | B6: OC-101 | C6: Confecciones Delta | D6: BUZ-001 | E6: Buzo Canguro con Frisa | F6: 29 | G6: 11960 | H6: 346840 | I6: 2026-03-20 | J6: PAGADO
A7: 2026-03-05 | B7: OC-101 | C7: Confecciones Delta | D7: BUZ-002 | E7: Buzo Canguro con Frisa | F7: 16 | G7: 11960 | H7: 191360 | I7: 2026-03-20 | J7: PAGADO
A8: 2026-03-05 | B8: OC-101 | C8: Sudaderas Arg | D8: BUZ-003 | E8: Buzo Cuello Redondo Premium | F8: 19 | G8: 13340 | H8: 253460 | I8: 2026-03-20 | J8: PAGADO
A9: 2026-03-05 | B9: OC-101 | C9: Abrigos Polar Sur | D9: CAM-001 | E9: Campera Trucker Impermeable | F9: 26 | G9: 23920 | H9: 621920 | I9: 2026-03-20 | J9: PAGADO
A10: 2026-03-05 | B10: OC-101 | C10: Abrigos Polar Sur | D10: CAM-002 | E10: Campera de Abrigo Invierno | F10: 21 | G10: 31280 | H10: 656880 | I10: 2026-03-20 | J10: PAGADO
A11: 2026-03-05 | B11: OC-101 | C11: Textil Avellaneda | D11: CAM-003 | E11: Campera Rompevientos Light | F11: 30 | G11: 14720 | H11: 441600 | I11: 2026-03-20 | J11: PAGADO
A12: 2026-03-05 | B12: OC-101 | C12: Jeans del Oeste | D12: PAN-001 | E12: Pantalón Jean Chupín | F12: 21 | G12: 15180 | H12: 318780 | I12: 2026-03-20 | J12: PAGADO
A13: 2026-03-05 | B13: OC-101 | C13: Jeans del Oeste | D13: PAN-002 | E13: Pantalón Jean Recto | F13: 26 | G13: 15180 | H13: 394680 | I13: 2026-03-20 | J13: PAGADO
... A43: 2026-05-14 | B43: OC-191 | C43: Lycra Activa | D43: TOP-002 | E43: Top Fitness Seamless | F43: 6 | G43: 6634 | H43: 39804 | I43: 2026-05-29 | J43: PENDIENTE

Sheet stock
A1: sku | B1: producto | C1: stock_inicial_marzo | D1: compras_marzo | E1: ventas_marzo | F1: stock_final_marzo | G1: compras_abril | H1: ventas_abril | I1: stock_final_abril | J1: compras_mayo | K1: ventas_mayo | L1: stock_final_mayo | M1: stock_minimo | N1: valor_stock_actual | O1: estado_stock
A2: REM-001 | B2: Remera Algodón Básica | C2: 65 | D2: 27 | E2: 32 | F2: =C2+D2-E2 | G2: 10 | H2: 38 | I2: =F2+G2-H2 | J2: 5 | K2: 0 | L2: =I2+J2-K2 | M2: 60 | N2: =L2*VLOOKUP(A2,productos!A:G,7,FALSE) | O2: bajo_minimo
A3: REM-002 | B3: Remera Algodón Básica | C3: 62 | D3: 23 | E3: 0 | F3: =C3+D3-E3 | G3: 13 | H3: 84 | I3: =F3+G3-H3 | J3: 8 | K3: 0 | L3: =I3+J3-K3 | M3: 60 | N3: =L3*VLOOKUP(A3,productos!A:G,7,FALSE) | O3: bajo_minimo
A4: REM-003 | B4: Remera Estampada Urban | C4: 44 | D4: 30 | E4: 25 | F4: =C4+D4-E4 | G4: 0 | H4: 3 | I4: =F4+G4-H4 | J4: 0 | K4: 0 | L4: =I4+J4-K4 | M4: 40 | N4: =L4*VLOOKUP(A4,productos!A:G,7,FALSE) | O4: ok
A5: REM-004 | B5: Remera Oversize Vint | C5: 64 | D5: 19 | E5: 6 | F5: =C5+D5-E5 | G5: 18 | H5: 7 | I5: =F5+G5-H5 | J5: 0 | K5: 0 | L5: =I5+J5-K5 | M5: 30 | N5: =L5*VLOOKUP(A5,productos!A:G,7,FALSE) | O5: sobrestock
A6: BUZ-001 | B6: Buzo Canguro con Frisa | C6: 68 | D6: 29 | E6: 6 | F6: =C6+D6-E6 | G6: 10 | H6: 6 | I6: =F6+G6-H6 | J6: 9 | K6: 0 | L6: =I6+J6-K6 | M6: 40 | N6: =L6*VLOOKUP(A6,productos!A:G,7,FALSE) | O6: sobrestock
A7: BUZ-002 | B7: Buzo Canguro con Frisa | C7: 72 | D7: 16 | E7: 1 | F7: =C7+D7-E7 | G7: 17 | H7: 5 | I7: =F7+G7-H7 | J7: 0 | K7: 4 | L7: =I7+J7-K7 | M7: 40 | N7: =L7*VLOOKUP(A7,productos!A:G,7,FALSE) | O7: ok
A8: BUZ-003 | B8: Buzo Cuello Redondo Premium | C8: 61 | D8: 19 | E8: 20 | F8: =C8+D8-E8 | G8: 0 | H8: 1 | I8: =F8+G8-H8 | J8: 0 | K8: 1 | L8: =I8+J8-K8 | M8: 25 | N8: =L8*VLOOKUP(A8,productos!A:G,7,FALSE) | O8: ok
A9: CAM-001 | B9: Campera Trucker Impermeable | C9: 68 | D9: 26 | E9: 1 | F9: =C9+D9-E9 | G9: 11 | H9: 4 | I9: =F9+G9-H9 | J9: 0 | K9: 0 | L9: =I9+J9-K9 | M9: 20 | N9: =L9*VLOOKUP(A9,productos!A:G,7,FALSE) | O9: sobrestock
A10: CAM-002 | B10: Campera de Abrigo Invierno | C10: 45 | D10: 21 | E10: 0 | F10: =C10+D10-E10 | G10: 40 | H10: 5 | I10: =F10+G10-H10 | J10: 0 | K10: 0 | L10: =I10+J10-K10 | M10: 15 | N10: =L10*VLOOKUP(A10,productos!A:G,7,FALSE) | O10: sobrestock
A11: CAM-003 | B11: Campera Rompevientos Light | C11: 73 | D11: 30 | E11: 0 | F11: =C11+D11-E11 | G11: 0 | H11: 4 | I11: =F11+G11-H11 | J11: 0 | K11: 2 | L11: =I11+J11-K11 | M11: 15 | N11: =L11*VLOOKUP(A11,productos!A:G,7,FALSE) | O11: sobrestock
A12: PAN-001 | B12: Pantalón Jean Chupín | C12: 65 | D12: 21 | E12: 4 | F12: =C12+D12-E12 | G12: 10 | H12: 108 | I12: =F12+G12-H12 | J12: 5 | K12: 0 | L12: =I12+J12-K12 | M12: 35 | N12: =L12*VLOOKUP(A12,productos!A:G,7,FALSE) | O12: bajo_minimo
A13: PAN-002 | B13: Pantalón Jean Recto | C13: 46 | D13: 26 | E13: 10 | F13: =C13+D13-E13 | G13: 0 | H13: 1 | I13: =F13+G13-H13 | J13: 0 | K13: 0 | L13: =I13+J13-K13 | M13: 30 | N13: =L13*VLOOKUP(A13,productos!A:G,7,FALSE) | O13: ok
... A23: ACC-003 | B23: Mochila Urbana Porta Notebook | C23: 14 | D23: 0 | E23: 3 | F23: =C23+D23-E23 | G23: 0 | H23: 10 | I23: =F23+G23-H23 | J23: 0 | K23: 0 | L23: =I23+J23-K23 | M23: 12 | N23: =L23*VLOOKUP(A23,productos!A:G,7,FALSE) | O23: sin_movimiento

Sheet costos_fijos
A1: mes | B1: concepto | C1: categoria | D1: importe | E1: vencimiento | F1: estado_pago
A2: marzo | B2: Alquiler Showroom y Depósito | C2: logística | D2: 450000 | E2: 2026-03-05 | F2: PAGADO
A3: marzo | B3: Sueldos Personal Confección/Ventas | C3: sueldos | D3: 1200000 | E3: 2026-03-05 | F3: PAGADO
A4: marzo | B4: Cargas Sociales F.931 | C4: impuestos | D4: 420000 | E4: 2026-03-15 | F4: PAGADO
A5: marzo | B5: Servicios (Luz, Internet, Gas) | C5: servicios | D5: 95000 | E5: 2026-03-10 | F5: PAGADO
A6: marzo | B6: Honorarios Contador | C6: contador | D6: 80000 | E6: 2026-03-10 | F6: PAGADO
A7: marzo | B7: Logística y Envíos (Andreani/Fletes) | C7: logística | D7: 150000 | E7: 2026-03-20 | F7: PAGADO
A8: marzo | B8: Marketing y Pauta Digital (Meta/Google) | C8: marketing | D8: 220000 | E8: 2026-03-18 | F8: PAGADO
A9: marzo | B9: Mantenimiento de Máquinas | C9: mantenimiento | D9: 45000 | E9: 2026-03-22 | F9: PAGADO
A10: marzo | B10: Software de Gestión y Tienda Cloud | C10: software | D10: 35000 | E10: 2026-03-10 | F10: PAGADO
A11: marzo | B11: Impuestos Provinciales / Tasas | C11: impuestos | D11: 60000 | E11: 2026-03-24 | F11: PAGADO
A12: abril | B12: Alquiler Showroom y Depósito | C12: logística | D12: 562500 | E12: 2026-04-05 | F12: PAGADO
A13: abril | B13: Sueldos Personal Confección/Ventas | C13: sueldos | D13: 1440000 | E13: 2026-04-05 | F13: PAGADO
... A31: mayo | B31: Impuestos Provinciales / Tasas | C31: impuestos | D31: 60000 | E31: 2026-05-24 | F31: PENDIENTE

Sheet caja_banco
A1: fecha | B1: tipo_movimiento | C1: concepto | D1: medio | E1: ingreso | F1: egreso | G1: saldo_estimado | H1: referencia
A2: 2026-03-01 | B2: ingreso | C2: Saldo Inicial de Caja | D2: transferencia | E2: 2500000 | F2: 0 | G2: =E2-F2 | H2: SALDO_INICIAL
A3: 2026-03-04 | B3: ingreso | C3: Cobro Venta REM-003 | D3: transferencia | E3: 46500 | F3: 0 | G3: =G2+E3-F3 | H3: VENTA_DIRECTA
A4: 2026-03-05 | B4: ingreso | C4: Cobro Venta MED-001 | D4: efectivo | E4: 16200 | F4: 0 | G4: =G3+E4-F4 | H4: VENTA_DIRECTA
A5: 2026-03-05 | B5: ingreso | C5: Cobro Venta CAL-001 | D5: mercado_pago | E5: 46000 | F5: 0 | G5: =G4+E5-F5 | H5: VENTA_DIRECTA
A6: 2026-03-05 | B6: ingreso | C6: Cobro Venta ACC-001 | D6: mercado_pago | E6: 31350 | F6: 0 | G6: =G5+E6-F6 | H6: VENTA_DIRECTA
A7: 2026-03-05 | B7: egreso | C7: Pago CF: Alquiler Showroom y Depósito | D7: transferencia | E7: 0 | F7: 450000 | G7: =G6+E7-F7 | H7: COSTO_FIJO
A8: 2026-03-05 | B8: egreso | C8: Pago CF: Sueldos Personal Confección/Ventas | D8: transferencia | E8: 0 | F8: 1200000 | G8: =G7+E8-F8 | H8: COSTO_FIJO
A9: 2026-03-07 | B9: ingreso | C9: Cobro Venta REM-003 | D9: mercado_pago | E9: 62000 | F9: 0 | G9: =G8+E9-F9 | H9: VENTA_DIRECTA
A10: 2026-03-07 | B10: ingreso | C10: Cobro Venta MED-002 | D10: transferencia | E10: 4370 | F10: 0 | G10: =G9+E10-F10 | H10: VENTA_DIRECTA
A11: 2026-03-07 | B11: ingreso | C11: Cobro Venta REM-004 | D11: transferencia | E11: 35600 | F11: 0 | G11: =G10+E11-F11 | H11: VENTA_DIRECTA
A12: 2026-03-08 | B12: ingreso | C12: Cobro Venta MED-001 | D12: mercado_pago | E12: 10800 | F12: 0 | G12: =G11+E12-F12 | H12: VENTA_DIRECTA
A13: 2026-03-08 | B13: ingreso | C13: Cobro Venta REM-001 | D13: mercado_pago | E13: 50000 | F13: 0 | G13: =G12+E13-F13 | H13: VENTA_DIRECTA
A14: 2026-03-08 | B14: ingreso | C14: Cobro Venta REM-001 | D14: transferencia | E14: 25000 | F14: 0 | G14: =G13+E14-F14 | H14: VENTA_DIRECTA
... A180: 2026-05-30 | B180: ingreso | C180: Cobro Venta TOP-001 | D180: mercado_pago | E180: 14900 | F180: 0 | G180: =G179+E180-F180 | H180: VENTA_DIRECTA

Sheet resumen_mensual
A1: mes | B1: ventas_brutas | C1: descuentos | D1: ventas_netas | E1: costo_variable | F1: margen_bruto | G1: margen_bruto_pct | H1: costos_fijos | I1: resultado_operativo | J1: stock_valorizado | K1: observacion
A2: marzo | B2: 6480000 | C2: 120000 | D2: =B2-C2 | E2: 2850000 | F2: =D2-E2 | G2: =F2/D2 | H2: 2705000 | I2: =F2-H2 | J2: 4820000 | K2: Operación saludable. Márgenes estables y stock balanceado.
A3: abril | B3: 12450000 | C3: 2950000 | D3: =B3-C3 | E3: 7420000 | F3: =D3-E3 | G3: =F3/D3 | H3: 3535000 | I3: =F3-H3 | J3: 7850000 | K3: CRISIS: Alto volumen de venta pero margen destruído por descuentos. Capital atrapado en stock de camperas.
A4: mayo | B4: 5120000 | C4: 80000 | D4: =B4-C4 | E4: 2310000 | F4: =D4-E4 | G4: =F4/D4 | H4: 2984000 | I4: =F4-H4 | J4: 7100000 | K4: Quiebre de stock en productos estrella por falta de caja para reposición. Estancamiento operativo.

Sheet señales_operativas
A1: señal_id | B1: mes | C1: tipo_señal | D1: descripción | E1: evidencia_relacionada | F1: severidad | G1: acción_sugerida
A2: SIG-001 | B2: abril | C2: margen_bajo | D2: Margen bruto consolidado cayó al 21.8%, muy por debajo del target general del 55%. | E2: Hoja Resumen Mensual, fila abril | F2: CRÍTICA | G2: Suspender promociones masivas del 30% en canales mayoristas sin escala mínima.
A3: SIG-002 | B3: abril | C3: sobrestock | D3: Capital inmovilizado de $3.4M en Campera de Abrigo (CAM-002) con bajísima rotación. | E3: Hoja stock, SKU CAM-002, 85 unidades finales | F3: ALTA | G3: Lanzar liquidación dirigida o canalizar stock mediante showrooms zonales.
A4: SIG-003 | B4: mayo | C4: stock_bajo | D4: Quiebre de stock inminente en Remeras Básicas (REM-001/REM-002). Stock por debajo del mínimo. | E4: Hoja stock, SKU REM-001 | F4: ALTA | G4: Priorizar saldos de caja para reponer este artículo; alta rotación asegurada.
A5: SIG-004 | B5: abril | C5: costo_fijo_alto | D5: Aumento del 50% en tarifas de servicios y 25% en alquileres tensionan el punto de equilibrio. | E5: Hoja costos_fijos, conceptos Alquiler y Servicios | F5: MEDIA | G5: Negociar plazos de pago de alquiler o revisar eficiencia energética del depósito.
A6: SIG-005 | B6: abril | C6: margen_negativo | D6: Ventas mayoristas a 'Distribuidora Centro' se realizaron con margen neto casi nulo por acumulación de descuento. | E6: Hoja ventas, cliente Distribuidora Centro | F6: CRÍTICA | G6: Establecer un límite estricto de descuento acumulable por sistema (máximo 15%).
A7: SIG-006 | B7: mayo | C7: caja_tensionada | D7: El saldo de caja proyectado cae a niveles mínimos históricos impidiendo compras de materia prima. | E7: Hoja caja_banco, saldos de mayo | F7: CRÍTICA | G7: Lanzar preventa online con cobro inmediato (descuento por efectivo/transferencia) para recuperar liquidez.
A8: SIG-007 | B8: abril | C8: compra_desalineada | D8: Compra masiva de insumos de invierno realizada tarde, lo que generó acumulación física e inmovilización. | E8: Hoja compras, OC-142 | F8: ALTA | G8: Planificar compras estacionales con 60 días de anticipación como mínimo.
A9: SIG-008 | B9: mayo | C9: precio_desactualizado | D9: Los costos de reposición subieron 7% en mayo pero los precios de lista minoristas están congelados desde marzo. | E9: Hoja productos vs compras_mayo | F9: ALTA | G9: Aplicar actualización de precios de lista de forma inmediata (+12%) para recomponer margen.
A10: SIG-009 | B10: marzo | C10: ok | D10: Desempeño operativo óptimo con rentabilidad neta superior al 15%. | E10: Hoja Resumen Mensual, fila marzo | F10: BAJA | G10: Mantener la estructura de costos controlada y replicar el mix de canales.
A11: SIG-010 | B11: abril | C11: caja_tensionada | D11: Fuerte retraso en cobranzas: Cuenta Corriente a 45 días pospone ingresos clave por $2.5M. | E11: Hoja ventas, plazos de cobro de abril | F11: ALTA | G11: Ofrecer descuento por pronto pago (ej. 5% desc por pago a 10 días) a clientes recurrentes.
